README.txt
setup.cfg
setup.py
ctsakim/__init__.py
ctsakim/ctsakim.py
ctsakim.egg-info/PKG-INFO
ctsakim.egg-info/SOURCES.txt
ctsakim.egg-info/dependency_links.txt
ctsakim.egg-info/not-zip-safe
ctsakim.egg-info/requires.txt
ctsakim.egg-info/top_level.txt