Metadata-Version: 1.0
Name: ctsakim
Version: 1.0.23
Summary: Cts akim okuma
Home-page: https://gitlab.com/ctsyazilim/ctsakim.git
Author: Soner Akarsu
Author-email: soner.akarsu@cts.com.tr
License: MIT
Platform: UNKNOWN
